langchain_kusto/__init__.py
langchain_kusto/vectorstore.py
langchain_kusto-0.0.1.dist-info/licenses/LICENSE
langchain_kusto-0.0.1.dist-info/METADATA
langchain_kusto-0.0.1.dist-info/WHEEL
langchain_kusto-0.0.1.dist-info/top_level.txt
langchain_kusto-0.0.1.dist-info/RECORD
