Metadata-Version: 2.4
Name: langchain-kusto
Version: 0.0.1
Summary: LangChain vector store implementation for Azure Data Explorer (Kusto) - PRE-ALPHA VERSION
Author-email: Daniel Dror <danield137@gmail.com>
Maintainer-email: Daniel Dror <danield137@gmail.com>
License: The MIT License (MIT)
Project-URL: Homepage, https://github.com/danield137/kusto_langchain
Project-URL: Bug Reports, https://github.com/danield137/kusto_langchain/issues
Project-URL: Source, https://github.com/danield137/kusto_langchain
Keywords: langchain,kusto,azure,eventhouse,fabric,data-explorer,vector-store,llm
Classifier: Development Status :: 2 - Pre-Alpha
Classifier: Intended Audience :: Developers
Classifier: License :: OSI Approved :: MIT License
Classifier: Operating System :: OS Independent
Classifier: Programming Language :: Python :: 3
Classifier: Programming Language :: Python :: 3.8
Classifier: Programming Language :: Python :: 3.9
Classifier: Programming Language :: Python :: 3.10
Classifier: Programming Language :: Python :: 3.11
Classifier: Programming Language :: Python :: 3.12
Classifier: Topic :: Software Development :: Libraries :: Python Modules
Classifier: Topic :: Scientific/Engineering :: Artificial Intelligence
Requires-Python: >=3.8
License-File: LICENSE
Requires-Dist: langchain-core>=0.1.0
Requires-Dist: azure-kusto-data>=4.2.0
Requires-Dist: azure-identity>=1.12.0
Provides-Extra: dev
Requires-Dist: pytest>=7.0; extra == "dev"
Requires-Dist: black>=22.0; extra == "dev"
Requires-Dist: isort>=5.0; extra == "dev"
Dynamic: license-file
